jsoncgx/__init__.py
jsoncgx/abstract.py
jsoncgx/lexer.py
jsoncgx/parser.py
jsoncgx/rexel.py
jsoncgx-1.1.dist-info/LICENCE
jsoncgx-1.1.dist-info/METADATA
jsoncgx-1.1.dist-info/WHEEL
jsoncgx-1.1.dist-info/top_level.txt
jsoncgx-1.1.dist-info/RECORD
