Metadata-Version: 2.1
Name: jsoncgx
Version: 1.1
Summary: An overpowered JSON-with-comments parser with inplace edition
Author-email: cigix <cigix@cigix.me>
Project-URL: Repository, https://github.com/cigix/jsoncgx
Project-URL: Issues, https://github.com/cigix/jsoncgx/issues
Keywords: json,jsonc,json with comments,json editor
Classifier: Development Status :: 5 - Production/Stable
Classifier: License :: OSI Approved :: GNU General Public License v3 or later (GPLv3+)
Classifier: Programming Language :: Python :: 3
Classifier: Topic :: File Formats :: JSON
Classifier: Typing :: Typed
Requires-Python: >=3.9
License-File: LICENCE
